feather_converter/__init__.py
feather_converter/converter.py
feather_converter-0.1.0.dist-info/entry_points.txt
feather_converter-0.1.0.dist-info/METADATA
feather_converter-0.1.0.dist-info/WHEEL
feather_converter-0.1.0.dist-info/RECORD
